ipylife/__init__.py
ipylife/_frontend.py
ipylife/_version.py
ipylife/life.py
ipylife/labextension/package.json
ipylife/labextension/static/480.4efa552d2f4013800911.js
ipylife/labextension/static/568.850a71498f11895c622a.js
ipylife/labextension/static/remoteEntry.39df6189f7e683d94d18.js
ipylife/labextension/static/style.js
ipylife/labextension/static/third-party-licenses.json
ipylife/nbextension/extension.js
ipylife/nbextension/index.js
ipylife/nbextension/index.js.map
ipylife/tests/__init__.py
ipylife/tests/conftest.py
ipylife/tests/test_life.py
ipylife/tests/test_nbextension_path.py
ipylife-0.1.0.data/data/etc/jupyter/nbconfig/notebook.d/ipylife.json
ipylife-0.1.0.data/data/share/jupyter/labextensions/ipylife/install.json
ipylife-0.1.0.data/data/share/jupyter/labextensions/ipylife/package.json
ipylife-0.1.0.data/data/share/jupyter/labextensions/ipylife/static/480.4efa552d2f4013800911.js
ipylife-0.1.0.data/data/share/jupyter/labextensions/ipylife/static/568.850a71498f11895c622a.js
ipylife-0.1.0.data/data/share/jupyter/labextensions/ipylife/static/remoteEntry.39df6189f7e683d94d18.js
ipylife-0.1.0.data/data/share/jupyter/labextensions/ipylife/static/style.js
ipylife-0.1.0.data/data/share/jupyter/labextensions/ipylife/static/third-party-licenses.json
ipylife-0.1.0.data/data/share/jupyter/nbextensions/ipylife/extension.js
ipylife-0.1.0.data/data/share/jupyter/nbextensions/ipylife/index.js
ipylife-0.1.0.data/data/share/jupyter/nbextensions/ipylife/index.js.map
ipylife-0.1.0.dist-info/LICENSE.txt
ipylife-0.1.0.dist-info/METADATA
ipylife-0.1.0.dist-info/WHEEL
ipylife-0.1.0.dist-info/top_level.txt
ipylife-0.1.0.dist-info/RECORD
